nekobox-0.1.6.dist-info/METADATA
nekobox-0.1.6.dist-info/WHEEL
nekobox-0.1.6.dist-info/entry_points.txt
nekobox-0.1.6.dist-info/licenses/LICENSE
nekobox/__init__.py
nekobox/__main__.py
nekobox/apis/__init__.py
nekobox/apis/handler.py
nekobox/apis/types.py
nekobox/apis/utils.py
nekobox/consts.py
nekobox/events/__init__.py
nekobox/events/handler.py
nekobox/events/utils.py
nekobox/log.py
nekobox/main.py
nekobox/msgid.py
nekobox/transformer.py
nekobox/uid.py
nekobox/utils.py
nekobox-0.1.6.dist-info/RECORD
