Metadata-Version: 2.1
Name: nekobox
Version: 0.1.6
Summary: A Satori backend powered by lagrange-python
Author-Email: wyapx <admin@nullcat.cn>, RF-Tar-Railt <rf_tar_railt@qq.com>
License: AGPL
Requires-Python: >=3.9
Requires-Dist: satori-python-server>=0.16.3
Requires-Dist: lagrange-python>=0.1.7
Provides-Extra: audio
Requires-Dist: pysilk-mod; extra == "audio"
